protcur/__init__.py
protcur/analysis.py
protcur/app.py
protcur/auth-config.py
protcur/cli.py
protcur/config.py
protcur/core.py
protcur/document.py
protcur/namespace_mappings.py
protcur/server.py
protcur/sparc.py
protcur-0.0.12.data/data/share/protcur/anno-tags.rkt
protcur-0.0.12.data/data/share/protcur/protc-tags.rkt
protcur-0.0.12.data/data/share/protcur/units/imperial-units-data.rkt
protcur-0.0.12.data/data/share/protcur/units/nist-tables.rkt
protcur-0.0.12.data/data/share/protcur/units/si-prefixes-data.rkt
protcur-0.0.12.data/data/share/protcur/units/si-prefixes-exp-data.rkt
protcur-0.0.12.data/data/share/protcur/units/si-units-data.rkt
protcur-0.0.12.data/data/share/protcur/units/si-units-extras.rkt
protcur-0.0.12.data/data/share/protcur/units/units-dimensionless.rkt
protcur-0.0.12.data/data/share/protcur/units/test/params.rkt
protcur-0.0.12.dist-info/LICENSE
protcur-0.0.12.dist-info/METADATA
protcur-0.0.12.dist-info/WHEEL
protcur-0.0.12.dist-info/entry_points.txt
protcur-0.0.12.dist-info/top_level.txt
protcur-0.0.12.dist-info/RECORD
