Metadata-Version: 2.1
Name: protcur
Version: 0.0.12
Summary: Web annotation workflows for protocol curation.
Home-page: https://github.com/tgbugs/protc/tree/master/protcur
Author: Tom Gillespie
Author-email: tgbugs@gmail.com
License: MIT
Keywords: protc protocols dashboard curation hypothesis hypothes.is web annotation
Classifier: Development Status :: 4 - Beta
Classifier: License :: OSI Approved :: MIT License
Classifier: Programming Language :: Python :: 3.7
Classifier: Programming Language :: Python :: 3.8
Classifier: Programming Language :: Python :: 3.9
Classifier: Programming Language :: Python :: 3.10
Classifier: Programming Language :: Python :: 3.11
Classifier: Programming Language :: Python :: 3.12
Classifier: Programming Language :: Python :: 3.13
Classifier: Programming Language :: Python :: Implementation :: CPython
Classifier: Programming Language :: Python :: Implementation :: PyPy
Classifier: Operating System :: POSIX :: Linux
Classifier: Operating System :: MacOS :: MacOS X
Classifier: Operating System :: Microsoft :: Windows
Requires-Python: >=3.7
License-File: LICENSE
Requires-Dist: flask
Requires-Dist: htmlfn
Requires-Dist: hyputils>=0.0.9
Requires-Dist: idlib>=0.0.1.dev22
Requires-Dist: Markdown
Requires-Dist: pyontutils>=0.1.26
Requires-Dist: pysercomb>=0.0.13
Provides-Extra: dev
Requires-Dist: pytest-cov; extra == "dev"
Requires-Dist: wheel; extra == "dev"
Provides-Extra: test
Requires-Dist: pytest; extra == "test"
